ngapp/__init__.py
ngapp/_version.py
ngapp/api.py
ngapp/app.py
ngapp/basecomponent.py
ngapp/create_app.py
ngapp/e2e.py
ngapp/file.py
ngapp/frontend_testing.py
ngapp/generate_metadata.py
ngapp/material.py
ngapp/pandoc_header.tex
ngapp/qcomponents.py
ngapp/test_utils.py
ngapp/utils.py
ngapp/visualization.py
ngapp/cli/__init__.py
ngapp/cli/build_website.py
ngapp/cli/generate_app_config.py
ngapp/cli/get_plugin_dirs.py
ngapp/cli/run.py
ngapp/cli/serve_app.py
ngapp/cli/serve_compute_env.py
ngapp/cli/serve_frontend.py
ngapp/cli/serve_in_venv.py
ngapp/cli/serve_standalone.py
ngapp/cli/utils.py
ngapp/cli/worker.py
ngapp/components/__init__.py
ngapp/components/basecomponent.py
ngapp/components/helper_components.py
ngapp/components/material.py
ngapp/components/qcomponents.py
ngapp/components/visualization.py
ngapp-0.2.11.dist-info/licenses/LICENSE
ngapp-0.2.11.dist-info/METADATA
ngapp-0.2.11.dist-info/WHEEL
ngapp-0.2.11.dist-info/top_level.txt
ngapp-0.2.11.dist-info/RECORD
