Metadata-Version: 2.4
Name: ngapp
Version: 0.2.11
Summary: A Python framework for building engineering and scientific web applications
License-Expression: LGPL-2.1-or-later
Requires-Python: >=3.10
License-File: LICENSE
Requires-Dist: certifi
Requires-Dist: orjson
Requires-Dist: pint
Requires-Dist: pydantic==2.*
Requires-Dist: urllib3
Requires-Dist: webgpu
Requires-Dist: numpy
Requires-Dist: colorama
Requires-Dist: platformdirs
Provides-Extra: dev
Requires-Dist: websockets; extra == "dev"
Requires-Dist: watchdog; extra == "dev"
Requires-Dist: wheel; extra == "dev"
Requires-Dist: setuptools; extra == "dev"
Requires-Dist: cookiecutter; extra == "dev"
Requires-Dist: deepdiff; extra == "dev"
Provides-Extra: e2e
Requires-Dist: pytest; extra == "e2e"
Requires-Dist: pytest-playwright; extra == "e2e"
Requires-Dist: pytest-check; extra == "e2e"
Requires-Dist: playwright; extra == "e2e"
Requires-Dist: pytest-base-url; extra == "e2e"
Dynamic: license-file
